pymegacli
