Metadata-Version: 1.1
Name: pymegacli
Version: 0.1.5.3
Summary: object-oriented API around the MegaCLI tool for administrating LSI RAID cards
Home-page: http://github.com/uber/pymegacli
Author: James Brown
Author-email: jbrown@uber.com
License: MIT
Platform: UNKNOWN
Classifier: Programming Language :: Python
Classifier: Operating System :: OS Independent
Classifier: License :: OSI Approved :: MIT License
Classifier: Topic :: System :: Hardware
Classifier: Topic :: System :: Monitoring
Classifier: Topic :: System :: Systems Administration
Classifier: Intended Audience :: System Administrators
Classifier: Development Status :: 4 - Beta
